ortho_codes/__init__.py
ortho_codes/hl7.py
ortho_codes/save_codes.py
ortho_codes/snomed.py
ortho_codes/vendors.py
open_ortho_codes-0.2.0.dist-info/LICENSE
open_ortho_codes-0.2.0.dist-info/METADATA
open_ortho_codes-0.2.0.dist-info/WHEEL
open_ortho_codes-0.2.0.dist-info/entry_points.txt
open_ortho_codes-0.2.0.dist-info/top_level.txt
open_ortho_codes-0.2.0.dist-info/RECORD
